Metadata-Version: 2.1
Name: atd-agol-util
Version: 0.0.7
Summary: Python utilities interacting with the ArcGIS Online (AGOL) API.
Home-page: https://github.com/cityofaustin/atd-data-utilities/tree/master/atd-agol-util
Author: City of Austin
Author-email: transportation.data@austintexas.gov
License: UNKNOWN
Platform: UNKNOWN
Classifier: Programming Language :: Python :: 3
Classifier: License :: Public Domain
Classifier: Operating System :: OS Independent
Classifier: Development Status :: 4 - Beta
Requires-Dist: requests
Requires-Dist: arcgis
